{
  "configurations": [
    {
      "name": "macos-clang-x64",
      "includePath": [
        "${workspaceFolder}/**"
      ],
      "defines": [],
      "macFrameworkPath": [
        "/System/Library/Frameworks"
      ],
      "compilerPath": "/usr/bin/clang",
      "cStandard": "${default}",
      "cppStandard": "${default}",
      "intelliSenseMode": "macos-clang-x64",
      "compileCommands": "/Users/andrewowen/Desktop/VEX24-25/Team5408ProsRepo-1/compile_commands.json",
      "browse": {
        "path": [
          "/Users/andrewowen/Team5408ProsRepo/Team5408ProsRepo"
        ],
        "limitSymbolsToIncludedHeaders": true,
        "databaseFilename": ""
      }
    }
  ],
  "version": 4
}